pygdbmi/IoManager.py
pygdbmi/StringStream.py
pygdbmi/__init__.py
pygdbmi/constants.py
pygdbmi/gdbcontroller.py
pygdbmi/gdbescapes.py
pygdbmi/gdbmiparser.py
pygdbmi/printcolor.py
pygdbmi/py.typed
pygdbmi_stop_on_result-0.12.0.0.dist-info/LICENSE
pygdbmi_stop_on_result-0.12.0.0.dist-info/METADATA
pygdbmi_stop_on_result-0.12.0.0.dist-info/WHEEL
pygdbmi_stop_on_result-0.12.0.0.dist-info/top_level.txt
pygdbmi_stop_on_result-0.12.0.0.dist-info/RECORD
