Metadata-Version: 2.1
Name: pygdbmi-stop-on-result
Version: 0.12.0.0
Summary: Parse gdb machine interface output with Python - fork to support fast return when a result is available
Home-page: https://github.com/noamraph/pygdbmi
Author: Noam Yorav-Raphael
Author-email: noamraph@gmail.com
License: MIT
Keywords: gdb,python,machine-interface,parse,frontend
Classifier: Intended Audience :: Developers
Classifier: License :: OSI Approved :: MIT License
Classifier: Operating System :: OS Independent
Classifier: Programming Language :: Python
Classifier: Programming Language :: Python :: 3
Classifier: Programming Language :: Python :: 3.7
Classifier: Programming Language :: Python :: 3.8
Classifier: Programming Language :: Python :: 3.9
Classifier: Programming Language :: Python :: 3.10
Classifier: Programming Language :: Python :: Implementation :: PyPy
License-File: LICENSE
